CHANGES.txt
LICENSE.txt
MANIFEST.in
README.md
requirements.txt
setup.py
django_social_friends_finder.egg-info/PKG-INFO
django_social_friends_finder.egg-info/SOURCES.txt
django_social_friends_finder.egg-info/dependency_links.txt
django_social_friends_finder.egg-info/not-zip-safe
django_social_friends_finder.egg-info/top_level.txt
social_friends_finder/__init__.py
social_friends_finder/admin.py
social_friends_finder/models.py
social_friends_finder/tests.py
social_friends_finder/urls.py
social_friends_finder/utils.py
social_friends_finder/views.py
social_friends_finder/.ropeproject/config.py
social_friends_finder/backends/__init__.py
social_friends_finder/backends/facebook_backend.py
social_friends_finder/backends/google_backend.py
social_friends_finder/backends/twitter_backend.py
social_friends_finder/fixtures/social_auth.json
social_friends_finder/fixtures/users.json
social_friends_finder/templates/social_friends_finder/friend_list.html