Metadata-Version: 1.0
Name: django-social-friends-finder
Version: 0.2
Summary: An extension app for django-social-auth or django-allauth that fetches your friends from different social-networks.
Home-page: https://github.com/laplacesdemon/django-social-friends-finder.git
Author: Suleyman Melikoglu
Author-email: suleyman@melikoglu.info
License: BSD licence, see LICENCE.txt
Platform: UNKNOWN
